Metadata-Version: 1.0
Name: recoo
Version: 0.1
Summary: Command line api for taste dive.
Home-page: UNKNOWN
Author: Kalpesh Adhatrao
Author-email: kalpesh.adhatrao@gmail.com
License: MIT
Platform: UNKNOWN
